wrc/__init__.py
wrc/version.py
wrc/wrc.py
wrc/codegen/__init__.py
wrc/codegen/cg.py
wrc/codegen/cghtml.py
wrc/codegen/cghtmltopdf.py
wrc/codegen/cgjson.py
wrc/codegen/merger.py
wrc/data/cmunbi.otf
wrc/data/cmunbx.otf
wrc/data/cmunrm.otf
wrc/data/cmunti.otf
wrc/data/footer.html
wrc/data/header.html
wrc/data/htmltopdf.css
wrc/data/languages.json
wrc/parse/__init__.py
wrc/parse/lexer.py
wrc/parse/parser.py
wrc/sema/__init__.py
wrc/sema/ast.py
wrc/sema/check.py
wrc-1.7.0.dist-info/licenses/LICENSE.txt
wrc-1.7.0.dist-info/METADATA
wrc-1.7.0.dist-info/WHEEL
wrc-1.7.0.dist-info/entry_points.txt
wrc-1.7.0.dist-info/top_level.txt
wrc-1.7.0.dist-info/RECORD
