Metadata-Version: 2.4
Name: wrc
Version: 1.7.0
Summary: Tool to build and perform checks on WCA Regulations and Guidelines
Author-email: Philippe Virouleau <philippe.44@gmail.com>, WCA Software Team <software@worldcubeassociation.org>
License: GPLv3
Project-URL: Homepage, https://github.com/thewca/wca-regulations-compiler
Project-URL: Issues, https://github.com/thewca/wca-regulations-compiler/issues
Requires-Python: >=3.9
License-File: LICENSE.txt
Requires-Dist: ply>=3.7
Requires-Dist: unidecode
Dynamic: license-file
